{"docs_components_alert.md":"B7oP5WrD","docs_components_avatar.md":"KPBQg621","docs_components_badge.md":"CAurYw2y","docs_components_breadcrumbs.md":"C7_WmhQZ","docs_components_button.md":"C-9vsAgD","docs_components_calendar.md":"IuEzkKlb","docs_components_charts.md":"Dmn4IXkE","docs_components_checkbox.md":"CUdyq_3j","docs_components_circularprogressbar.md":"D1F3uaUi","docs_components_codeeditor.md":"C5TItAJN","docs_components_combobox.md":"DMmnLVL7","docs_components_contextmenu.md":"Cro4CJVg","docs_components_datepicker.md":"uFRkKaAK","docs_components_dialog.md":"D3xnlk0e","docs_components_divider.md":"BBil-HOy","docs_components_dropdown.md":"9klKglfZ","docs_components_duration.md":"DhjaUqbJ","docs_components_errormessage.md":"DpQ8pGMP","docs_components_fileuploader.md":"CTj3gtvz","docs_components_formcontrol.md":"Dp6OxDVK","docs_components_itemlistrow.md":"ChnplS53","docs_components_keyboardshortcutsmodal.md":"s9P7F8G_","docs_components_legacy.md":"B-4ZBc0K","docs_components_listview.md":"Cb5Kb0M5","docs_components_monthpicker.md":"B6kIjIWy","docs_components_multiselect.md":"4r_avC5R","docs_components_password.md":"CMVC3zAS","docs_components_pill.md":"BTJBq-pJ","docs_components_popover.md":"BJllI91C","docs_components_progress.md":"CHeRl5uP","docs_components_rating.md":"BRxmAK1q","docs_components_select.md":"dAX4zVyz","docs_components_sidebar.md":"LbWfZp21","docs_components_slider.md":"blXmHYXs","docs_components_spinner.md":"rPUI098A","docs_components_switch.md":"DK4JoFLn","docs_components_tabbuttons.md":"D4h5apvl","docs_components_tabs.md":"JYP_tlGb","docs_components_textarea.md":"CIz4o701","docs_components_texteditor.md":"go_XfGoS","docs_components_textinput.md":"BiOzWVgl","docs_components_themeswitcher.md":"CuTrnb0i","docs_components_timepicker.md":"CvFHg0t0","docs_components_toast.md":"D8frT3gA","docs_components_tooltip.md":"CIfRdmMZ","docs_components_tree.md":"CDrXsY79","docs_data-fetching_document-resource.md":"DJuhGXII","docs_data-fetching_list-resource.md":"BVLgWQPZ","docs_data-fetching_resource.md":"Dev-KMCW","docs_foundations_colors_base.md":"DWJZRJvZ","docs_foundations_colors_semantic.md":"mT_l-WgE","docs_foundations_elevation.md":"DHMuz_9A","docs_foundations_focus-ring.md":"D7HN0JTP","docs_foundations_radius.md":"D-klDB3y","docs_foundations_typography.md":"BAtOREgX","docs_frappe_link.md":"RUhouYRB","docs_getting-started.md":"X6TmPmPW","docs_internals.md":"BkOQLMPZ","docs_introduction.md":"DqXd0In5","docs_migration.md":"PEhJnPqZ","docs_molecules_editor.md":"CfqwuzZE","docs_other_directives.md":"VPajBeuS","docs_other_icons.md":"Uyaw2ywT","docs_other_utilities.md":"CS-7ee9a","index.md":"Dnk1hcR2"}
